triptan
