Metadata-Version: 1.0
Name: triptan
Version: 1.0.6
Summary: Datastore independent migration tool
Home-page: https://github.com/alexanderjulo/triptan
Author: Alexander Jung-Loddenkemper
Author-email: alexander@julo.ch
License: UNKNOWN
Platform: UNKNOWN
